pkg1/__init__.py
pkg1/test.py
pkg2/__init__.py
pkg2/test.py
mytestlibrarykk-0.0.1.dist-info/METADATA
mytestlibrarykk-0.0.1.dist-info/WHEEL
mytestlibrarykk-0.0.1.dist-info/top_level.txt
mytestlibrarykk-0.0.1.dist-info/RECORD
